separatrice_temp/__init__.py
separatrice_temp/separatrice.py
separatrice_temp-1.6.4.dist-info/METADATA
separatrice_temp-1.6.4.dist-info/WHEEL
separatrice_temp-1.6.4.dist-info/top_level.txt
separatrice_temp-1.6.4.dist-info/RECORD
