Metadata-Version: 2.1
Name: separatrice-temp
Version: 1.6.4
Summary: Separatrice is able to split a text into sentences and a sentence into clauses (russian). See docs: github.com/constantin50/separatrice/
Home-page: https://github.com/constantin50/separatrice
Author: Constantin Werner
Author-email: const.werner@gmail.com
License: MIT
Keywords: tokenizer,segmentation,NLP,russian,clauses
Platform: UNKNOWN
Classifier: Programming Language :: Python :: 3
Classifier: License :: OSI Approved :: MIT License
Classifier: Operating System :: OS Independent
Requires-Dist: nltk
